LICENSE
README.md
setup.py
latest_chromedriver/__init__.py
latest_chromedriver/__main__.py
latest_chromedriver/chrome_info.py
latest_chromedriver/download_driver.py
latest_chromedriver/enviroment.py
latest_chromedriver/version.py
latest_chromedriver.egg-info/PKG-INFO
latest_chromedriver.egg-info/SOURCES.txt
latest_chromedriver.egg-info/dependency_links.txt
latest_chromedriver.egg-info/entry_points.txt
latest_chromedriver.egg-info/requires.txt
latest_chromedriver.egg-info/top_level.txt