Metadata-Version: 2.1
Name: latest-chromedriver
Version: 2022.6.30
Summary: A small package to find the correct chromedriver version in windows machines
Home-page: https://github.com/hargikas/auto-chromedriver/
Author: Charalampos Gkikas
Author-email: hargikas@gmail.com
License: MIT
Project-URL: Say Thanks!, https://saythanks.io/to/hargikas
Project-URL: Source, https://github.com/hargikas/auto-chromedriver/
Project-URL: Tracker, https://github.com/hargikas/auto-chromedriver/issues
Keywords: chromedriver windows
Classifier: Development Status :: 4 - Beta
Classifier: Programming Language :: Python :: 3
Classifier: License :: OSI Approved :: MIT License
Classifier: Operating System :: Microsoft :: Windows
Requires-Python: >=3
License-File: LICENSE
